{
  "character_id": 129,
  "character_name": "JOHNSON",
  "category": "D",
  "first_names": "Samuel",
  "birth_date": "1709",
  "death_date": "1784 (75yrs)",
  "wikimedia_title": "File:Portrait of Samuel Johnson (\"Blinking Sam\").jpg",
  "wikimedia_url": "https://upload.wikimedia.org/wikipedia/commons/4/44/Portrait_of_Samuel_Johnson_%28%22Blinking_Sam%22%29.jpg",
  "page_url": "https://commons.wikimedia.org/wiki/File:Portrait_of_Samuel_Johnson_(\"Blinking_Sam\").jpg",
  "width": 826,
  "height": 1000,
  "aspect_ratio": 1.211,
  "score": 0.7998626361648621,
  "candidate_rank": 4,
  "rank": 1,
  "selected_option": 4,
  "selection_timestamp": "2025-11-16T23:29:37.746461",
  "quality_score": 0.667,
  "ratio_score": 0.831,
  "resolution_score": 0.285,
  "meets_strict_requirements": [],
  "score_updated": "2025-11-18T23:32:07.779266",
  "orientation": "portrait"
}