{
  "character_id": 189,
  "character_name": "NOTRE DAME",
  "category": "B",
  "first_names": "CATHEDRAL",
  "birth_date": "1163",
  "death_date": "1240",
  "wikimedia_title": "File:Paris, Notre Dame -- 2014 -- 1434.jpg",
  "wikimedia_url": "https://upload.wikimedia.org/wikipedia/commons/3/3c/Paris%2C_Notre_Dame_--_2014_--_1434.jpg",
  "page_url": "https://commons.wikimedia.org/wiki/File:Paris,_Notre_Dame_--_2014_--_1434.jpg",
  "width": 3428,
  "height": 5303,
  "aspect_ratio": 1.547,
  "score": 0.9179637114334924,
  "candidate_rank": 5,
  "quality_score": 0.918,
  "ratio_score": 0.883,
  "resolution_score": 1.0,
  "meets_strict_requirements": [],
  "score_updated": "2025-11-18T20:50:24.268822",
  "orientation": "portrait"
}