{
  "character_name": "FREDERICK II",
  "character_id": 92,
  "category": "R",
  "first_names": "(the Great)",
  "biography": "R19, King of Prussia,  r. 1740-1786 (46yrs)",
  "birth_date": "1712",
  "death_date": "1786 (74yrs)",
  "width": 3057,
  "height": 3462,
  "aspect_ratio": 1.132,
  "quality_score": 0.842,
  "ratio_score": 0.78,
  "resolution_score": 0.987,
  "meets_strict_requirements": [],
  "source": "metadata_generation",
  "download_timestamp": "2025-11-12T00:32:25.790215",
  "rank": 1,
  "score_updated": "2025-11-18T19:01:09.604807",
  "orientation": "portrait"
}